guess_testing/__init__.py
guess_testing/__main__.py
guess_testing/_base_generator.py
guess_testing/cli.py
guess_testing/generators.py
guess_testing/guess.py
guess_testing/tracing.py
guess_testing/typing_generators_factory.py
guess_testing-2.0.0.dist-info/LICENCE.txt
guess_testing-2.0.0.dist-info/METADATA
guess_testing-2.0.0.dist-info/WHEEL
guess_testing-2.0.0.dist-info/entry_points.txt
guess_testing-2.0.0.dist-info/top_level.txt
guess_testing-2.0.0.dist-info/RECORD
